SLCs/Counters/freq_div/freq_div.v
module freq_div (
    input clk,
    input din,
    input reset,
    output reg out
);
    
    always @(negedge clk or reset) begin
        if(reset) out <= 0;
        else if(~din) out <= 0;
        else if(din) out <= ~out;
        else out <= out;
    end
endmodule

SLCs/Counters/freq_div/tb.v
`include "freq_div.v"
`timescale 1ns / 1ns

module freq_div_tb;
    reg clk, din, r;
    wire out;

    freq_div uut (
        .clk(clk),
        .din(din),
        .reset(r),
        .out(out)
    );

    always #1 clk = ~clk;
 
    initial begin
        $dumpfile("freq_div_tb.vcd");
        $dumpvars(0, freq_div_tb);
        r = 1;
        #1
        r = 0;
        clk = 0;
        din = 1;
        repeat(100) @(negedge clk);
        $finish;
    end

endmodule

SLCs/Counters/freq_div/freq_div_tb.vcd
$date
	Fri May 17 11:51:42 2024
$end
$version
	Icarus Verilog
$end
$timescale
	1ns
$end
$scope module freq_div_tb $end
$var wire 1 ! out $end
$var reg 1 " clk $end
$var reg 1 # din $end
$var reg 1 $ r $end
$scope module uut $end
$var wire 1 % clk $end
$var wire 1 & din $end
$var wire 1 ' reset $end
$var reg 1 ( out $end
$upscope $end
$upscope $end
$enddefinitions $end
#0
$dumpvars
0(
1'
x&
x%
1$
x#
x"
0!
$end
#1
1(
1!
1#
1&
0"
0%
0$
0'
#2
1"
1%
#3
0(
0!
0"
0%
#4
1"
1%
#5
1(
1!
0"
0%
#6
1"
1%
#7
0(
0!
0"
0%
#8
1"
1%
#9
1(
1!
0"
0%
#10
1"
1%
#11
0(
0!
0"
0%
#12
1"
1%
#13
1(
1!
0"
0%
#14
1"
1%
#15
0(
0!
0"
0%
#16
1"
1%
#17
1(
1!
0"
0%
#18
1"
1%
#19
0(
0!
0"
0%
#20
1"
1%
#21
1(
1!
0"
0%
#22
1"
1%
#23
0(
0!
0"
0%
#24
1"
1%
#25
1(
1!
0"
0%
#26
1"
1%
#27
0(
0!
0"
0%
#28
1"
1%
#29
1(
1!
0"
0%
#30
1"
1%
#31
0(
0!
0"
0%
#32
1"
1%
#33
1(
1!
0"
0%
#34
1"
1%
#35
0(
0!
0"
0%
#36
1"
1%
#37
1(
1!
0"
0%
#38
1"
1%
#39
0(
0!
0"
0%
#40
1"
1%
#41
1(
1!
0"
0%
#42
1"
1%
#43
0(
0!
0"
0%
#44
1"
1%
#45
1(
1!
0"
0%
#46
1"
1%
#47
0(
0!
0"
0%
#48
1"
1%
#49
1(
1!
0"
0%
#50
1"
1%
#51
0(
0!
0"
0%
#52
1"
1%
#53
1(
1!
0"
0%
#54
1"
1%
#55
0(
0!
0"
0%
#56
1"
1%
#57
1(
1!
0"
0%
#58
1"
1%
#59
0(
0!
0"
0%
#60
1"
1%
#61
1(
1!
0"
0%
#62
1"
1%
#63
0(
0!
0"
0%
#64
1"
1%
#65
1(
1!
0"
0%
#66
1"
1%
#67
0(
0!
0"
0%
#68
1"
1%
#69
1(
1!
0"
0%
#70
1"
1%
#71
0(
0!
0"
0%
#72
1"
1%
#73
1(
1!
0"
0%
#74
1"
1%
#75
0(
0!
0"
0%
#76
1"
1%
#77
1(
1!
0"
0%
#78
1"
1%
#79
0(
0!
0"
0%
#80
1"
1%
#81
1(
1!
0"
0%
#82
1"
1%
#83
0(
0!
0"
0%
#84
1"
1%
#85
1(
1!
0"
0%
#86
1"
1%
#87
0(
0!
0"
0%
#88
1"
1%
#89
1(
1!
0"
0%
#90
1"
1%
#91
0(
0!
0"
0%
#92
1"
1%
#93
1(
1!
0"
0%
#94
1"
1%
#95
0(
0!
0"
0%
#96
1"
1%
#97
1(
1!
0"
0%
#98
1"
1%
#99
0(
0!
0"
0%
#100
1"
1%
#101
1(
1!
0"
0%
#102
1"
1%
#103
0(
0!
0"
0%
#104
1"
1%
#105
1(
1!
0"
0%
#106
1"
1%
#107
0(
0!
0"
0%
#108
1"
1%
#109
1(
1!
0"
0%
#110
1"
1%
#111
0(
0!
0"
0%
#112
1"
1%
#113
1(
1!
0"
0%
#114
1"
1%
#115
0(
0!
0"
0%
#116
1"
1%
#117
1(
1!
0"
0%
#118
1"
1%
#119
0(
0!
0"
0%
#120
1"
1%
#121
1(
1!
0"
0%
#122
1"
1%
#123
0(
0!
0"
0%
#124
1"
1%
#125
1(
1!
0"
0%
#126
1"
1%
#127
0(
0!
0"
0%
#128
1"
1%
#129
1(
1!
0"
0%
#130
1"
1%
#131
0(
0!
0"
0%
#132
1"
1%
#133
1(
1!
0"
0%
#134
1"
1%
#135
0(
0!
0"
0%
#136
1"
1%
#137
1(
1!
0"
0%
#138
1"
1%
#139
0(
0!
0"
0%
#140
1"
1%
#141
1(
1!
0"
0%
#142
1"
1%
#143
0(
0!
0"
0%
#144
1"
1%
#145
1(
1!
0"
0%
#146
1"
1%
#147
0(
0!
0"
0%
#148
1"
1%
#149
1(
1!
0"
0%
#150
1"
1%
#151
0(
0!
0"
0%
#152
1"
1%
#153
1(
1!
0"
0%
#154
1"
1%
#155
0(
0!
0"
0%
#156
1"
1%
#157
1(
1!
0"
0%
#158
1"
1%
#159
0(
0!
0"
0%
#160
1"
1%
#161
1(
1!
0"
0%
#162
1"
1%
#163
0(
0!
0"
0%
#164
1"
1%
#165
1(
1!
0"
0%
#166
1"
1%
#167
0(
0!
0"
0%
#168
1"
1%
#169
1(
1!
0"
0%
#170
1"
1%
#171
0(
0!
0"
0%
#172
1"
1%
#173
1(
1!
0"
0%
#174
1"
1%
#175
0(
0!
0"
0%
#176
1"
1%
#177
1(
1!
0"
0%
#178
1"
1%
#179
0(
0!
0"
0%
#180
1"
1%
#181
1(
1!
0"
0%
#182
1"
1%
#183
0(
0!
0"
0%
#184
1"
1%
#185
1(
1!
0"
0%
#186
1"
1%
#187
0(
0!
0"
0%
#188
1"
1%
#189
1(
1!
0"
0%
#190
1"
1%
#191
0(
0!
0"
0%
#192
1"
1%
#193
1(
1!
0"
0%
#194
1"
1%
#195
0(
0!
0"
0%
#196
1"
1%
#197
1(
1!
0"
0%
#198
1"
1%
#199
0(
0!
0"
0%
#200
1"
1%
#201
1(
1!
0"
0%
