CLCs/arithmetic logic circuits/subtractor/subtractor.v
module subtractor #(parameter WIDTH = 8) (
    input [WIDTH-1:0] a,
    input [WIDTH-1:0] b,
    output reg [WIDTH-1:0] result,
    output reg borrow
);

always @(*) begin
    result = a - b;
    if (a >= b) begin
        borrow = 0;
    end else begin
        borrow = 1;
    end
end

endmodule

CLCs/arithmetic logic circuits/subtractor/tb.v
`include "subtractor.v"
`default_nettype none

module tb_subtractor;

reg [3:0] a_in, b_in;
wire [3:0] result_out;
wire borrow;

subtractor #(4) sub
(
    .a(a_in),
    .b(b_in),
    .result(result_out),
    .borrow(borrow)
);

initial begin
    $dumpfile("tb_subtractor.vcd");
    $dumpvars(0, tb_subtractor);
end

initial begin
    a_in = 4'b0000;
    b_in = 4'b0000;
    #10;
    a_in = 4'b0000;
    b_in = 4'b0001;
    #10;
    a_in = 4'b0001;
    b_in = 4'b0000;
    #10;
    a_in = 4'b0001;
    b_in = 4'b0001;
    #10;
    a_in = 4'b0000;
    b_in = 4'b0001;
    #10;
    a_in = 4'b0001;
    b_in = 4'b0000;
    #10;
    a_in = 4'b0001;
    b_in = 4'b0001;
    #10;
    a_in = 4'b0000;
    b_in = 4'b0001;
    #10;
    a_in = 4'b0001;
    b_in = 4'b0000;
    #10;
    a_in = 4'b0001;
    b_in = 4'b0001;
    #10;
    $finish;
end

endmodule
`default_nettype wire

CLCs/arithmetic logic circuits/subtractor/tb_subtractor.vcd
$date
	Fri May 03 10:01:29 2024
$end
$version
	Icarus Verilog
$end
$timescale
	1s
$end
$scope module tb_subtractor $end
$var wire 1 ! borrow $end
$var wire 4 " result_out [3:0] $end
$var reg 4 # a_in [3:0] $end
$var reg 4 $ b_in [3:0] $end
$scope module sub $end
$var wire 4 % a [3:0] $end
$var wire 4 & b [3:0] $end
$var reg 1 ' borrow $end
$var reg 4 ( result [3:0] $end
$upscope $end
$upscope $end
$enddefinitions $end
#0
$dumpvars
b0 (
0'
b0 &
b0 %
b0 $
b0 #
b0 "
0!
$end
#10
1'
1!
b1111 (
b1111 "
b1 $
b1 &
#20
0'
0!
b1 (
b1 "
b0 $
b0 &
b1 #
b1 %
#30
b0 (
b0 "
b1 $
b1 &
#40
1'
1!
b1111 (
b1111 "
b0 #
b0 %
#50
0'
0!
b1 (
b1 "
b0 $
b0 &
b1 #
b1 %
#60
b0 (
b0 "
b1 $
b1 &
#70
1'
1!
b1111 (
b1111 "
b0 #
b0 %
#80
0'
0!
b1 (
b1 "
b0 $
b0 &
b1 #
b1 %
#90
b0 (
b0 "
b1 $
b1 &
