CLCs/encoders/prioencoder.v
// in a priority encoder 2^n inputs is to n outputs
// priority 4-2 encoder truth table
// 0000 -> 00
// 0001 -> 01
// 0010 -> 10
// 0100 -> 11

module priority_encoder #(
    parameter m = 4,
    parameter n = 2
) (
    input [m-1:0] in,
    output reg [n-1:0] out
);

    integer i;

    always @(*) begin
        out = {n{1'b0}}; // Initialize output to all zeros
        for(i = 0; i < m; i = i + 1) begin
            if(in[i] == 1'b1) begin
                out = i;
            end
        end
    end
endmodule

CLCs/encoders/tb.v
`include "prioencoder.v"

`default_nettype none

module tb_prioencoder;
    reg [7:0] in;
    wire [2:0] out;

    priority_encoder #(
        .m(8),
        .n(3)
        ) prioencoder(
            .in(in),
            .out(out)
    );

initial begin
    $dumpfile("tb_prioencoder.vcd");
    $dumpvars(0, tb_prioencoder);
end

integer i;

initial begin
    $monitor("in=%b, out=%b", in, out);
    for(i = 0; i < 8; i = i + 1) begin
        in = 1'b1 << i;
        #10;
    end

    #10;
    in = 8'b00001101;
    $finish;


end

endmodule
`default_nettype wire

CLCs/encoders/tb_prioencoder.vcd
$date
	Thu May 09 07:13:03 2024
$end
$version
	Icarus Verilog
$end
$timescale
	1s
$end
$scope module tb_prioencoder $end
$var wire 3 ! out [2:0] $end
$var integer 32 " i [31:0] $end
$var reg 8 # in [7:0] $end
$scope module prioencoder $end
$var wire 8 $ in [7:0] $end
$var integer 32 % i [31:0] $end
$var reg 3 & out [2:0] $end
$upscope $end
$upscope $end
$enddefinitions $end
#0
$dumpvars
b0 &
b1000 %
b1 $
b1 #
b0 "
b0 !
$end
#10
b1 &
b1 !
b1000 %
b10 #
b10 $
b1 "
#20
b1000 %
b10 &
b10 !
b100 #
b100 $
b10 "
#30
b1000 %
b11 &
b11 !
b1000 #
b1000 $
b11 "
#40
b1000 %
b100 &
b100 !
b10000 #
b10000 $
b100 "
#50
b1000 %
b101 &
b101 !
b100000 #
b100000 $
b101 "
#60
b1000 %
b110 &
b110 !
b1000000 #
b1000000 $
b110 "
#70
b1000 %
b111 &
b111 !
b10000000 #
b10000000 $
b111 "
#80
b1000 "
#90
b1000 %
b11 &
b11 !
b1101 #
b1101 $
